{
  "de": {
    "translated": 731,
    "notTranslated": 24,
    "added": [
      "Checklists.CalcifiedLight.Prefix",
      "Checklists.SavathunsEyes.Prefix"
    ],
    "removed": [
      "Eye",
      "Fragment"
    ]
  },
  "debug": {
    "translated": 755,
    "notTranslated": 0,
    "added": [
      "Checklists.CalcifiedLight.Prefix",
      "Checklists.SavathunsEyes.Prefix"
    ],
    "removed": [
      "Eye",
      "Fragment"
    ]
  },
  "en": {
    "translated": 755,
    "notTranslated": 0,
    "added": [],
    "removed": [
      "Eye",
      "Fragment"
    ]
  },
  "es-mx": {
    "translated": 747,
    "notTranslated": 8,
    "added": [
      "Checklists.CalcifiedLight.Prefix",
      "Checklists.SavathunsEyes.Prefix"
    ],
    "removed": [
      "Eye",
      "Fragment"
    ]
  },
  "es": {
    "translated": 747,
    "notTranslated": 8,
    "added": [
      "Checklists.CalcifiedLight.Prefix",
      "Checklists.SavathunsEyes.Prefix"
    ],
    "removed": [
      "Eye",
      "Fragment"
    ]
  },
  "fr": {
    "translated": 622,
    "notTranslated": 133,
    "added": [
      "Checklists.CalcifiedLight.Prefix",
      "Checklists.SavathunsEyes.Prefix"
    ],
    "removed": [
      "Eye",
      "Fragment"
    ]
  },
  "it": {
    "translated": 744,
    "notTranslated": 11,
    "added": [
      "Checklists.CalcifiedLight.Prefix",
      "Checklists.SavathunsEyes.Prefix"
    ],
    "removed": [
      "Eye",
      "Fragment"
    ]
  },
  "ja": {
    "translated": 601,
    "notTranslated": 154,
    "added": [
      "Checklists.CalcifiedLight.Prefix",
      "Checklists.SavathunsEyes.Prefix"
    ],
    "removed": [
      "Eye",
      "Fragment"
    ]
  },
  "ko": {
    "translated": 514,
    "notTranslated": 241,
    "added": [
      "Checklists.CalcifiedLight.Prefix",
      "Checklists.SavathunsEyes.Prefix"
    ],
    "removed": [
      "Eye",
      "Fragment"
    ]
  },
  "pl": {
    "translated": 2,
    "notTranslated": 753,
    "added": [
      "Checklists.CalcifiedLight.Prefix",
      "Checklists.SavathunsEyes.Prefix"
    ],
    "removed": [
      "Eye",
      "Fragment"
    ]
  },
  "pt-br": {
    "translated": 706,
    "notTranslated": 49,
    "added": [
      "Checklists.CalcifiedLight.Prefix",
      "Checklists.SavathunsEyes.Prefix"
    ],
    "removed": [
      "Eye",
      "Fragment"
    ]
  },
  "ru": {
    "translated": 747,
    "notTranslated": 8,
    "added": [
      "Checklists.CalcifiedLight.Prefix",
      "Checklists.SavathunsEyes.Prefix"
    ],
    "removed": [
      "Eye",
      "Fragment"
    ]
  },
  "zh-chs": {
    "translated": 563,
    "notTranslated": 192,
    "added": [
      "Checklists.CalcifiedLight.Prefix",
      "Checklists.SavathunsEyes.Prefix"
    ],
    "removed": [
      "Eye",
      "Fragment"
    ]
  },
  "zh-cht": {
    "translated": 349,
    "notTranslated": 406,
    "added": [
      "Checklists.CalcifiedLight.Prefix",
      "Checklists.SavathunsEyes.Prefix"
    ],
    "removed": [
      "Eye",
      "Fragment"
    ]
  }
}